isle/__init__.py
isle/_api.py
isle/_config.py
isle/_requests.py
isle/_urls.py
isle/movie.py
isle/objects.py
isle/people.py
isle/show.py
isle-0.6.0.dist-info/LICENSE
isle-0.6.0.dist-info/WHEEL
isle-0.6.0.dist-info/METADATA
isle-0.6.0.dist-info/RECORD
